nptorch/__init__.py
nptorch/core.py
nptorch/optim.py
nptorch/nn/__init__.py
nptorch/nn/functional.py
nptorch/nn/functional_classes.py
nptorch/nn/nn_core.py
nptorch-0.0.2.dist-info/METADATA
nptorch-0.0.2.dist-info/WHEEL
nptorch-0.0.2.dist-info/top_level.txt
nptorch-0.0.2.dist-info/RECORD
